wbg/comms/__init__.py
wbg/comms/_comms.py
wbg/comms/_email_accounts.py
wbg/comms/_paths.py
wbg/comms/py.typed
wbg_comms-1.0.0.dist-info/METADATA
wbg_comms-1.0.0.dist-info/WHEEL
wbg_comms-1.0.0.dist-info/top_level.txt
wbg_comms-1.0.0.dist-info/RECORD
